LICENSE
README.md
pyproject.toml
setup.py
tests/test_api.py
tests/test_data_sources.py
tests/test_grids.py
tests/test_sample_nc.py
tests/test_variable_codes.py
wiwb/__init__.py
wiwb/api.py
wiwb/auth.py
wiwb/constants.py
wiwb/converters.py
wiwb/sample.py
wiwb.egg-info/PKG-INFO
wiwb.egg-info/SOURCES.txt
wiwb.egg-info/dependency_links.txt
wiwb.egg-info/requires.txt
wiwb.egg-info/top_level.txt
wiwb.egg-info/zip-safe
wiwb/api_calls/__init__.py
wiwb/api_calls/base.py
wiwb/api_calls/body.py
wiwb/api_calls/get_data_sources.py
wiwb/api_calls/get_grids.py
wiwb/api_calls/get_variables.py