Metadata-Version: 2.4
Name: wiwb
Version: 2025.11.0
Summary: Python API to work with WIWB
Author-email: Daniel Tollenaar <daniel@d2hydro.nl>, Renier Kramer <renier.kramer@hdsr.nl>
License: MIT
Project-URL: Source, https://github.com/d2hydro/wiwb
Requires-Python: <3.14,>=3.9
License-File: LICENSE
Requires-Dist: geopandas
Requires-Dist: pyjwt
Requires-Dist: netcdf4
Requires-Dist: xarray
Requires-Dist: rasterio
Requires-Dist: rasterstats
Requires-Dist: requests
Requires-Dist: affine
Requires-Dist: rioxarray
Provides-Extra: tests
Requires-Dist: pytest; extra == "tests"
Dynamic: license-file
